jupyter_console/__init__.py
jupyter_console/__main__.py
jupyter_console/_version.py
jupyter_console/app.py
jupyter_console/completer.py
jupyter_console/ptshell.py
jupyter_console/utils.py
jupyter_console/zmqhistory.py
jupyter_console/tests/__init__.py
jupyter_console/tests/conftest.py
jupyter_console/tests/test_console.py
jupyter_console/tests/test_image_handler.py
jupyter_console/tests/writetofile.py
jupyter_console-6.5.1.dist-info/LICENSE
jupyter_console-6.5.1.dist-info/METADATA
jupyter_console-6.5.1.dist-info/WHEEL
jupyter_console-6.5.1.dist-info/entry_points.txt
jupyter_console-6.5.1.dist-info/top_level.txt
jupyter_console-6.5.1.dist-info/RECORD
